unet/__init__.py
unet/conv.py
unet/decoding.py
unet/encoding.py
unet/unet.py
unet-0.8.0.dist-info/METADATA
unet-0.8.0.dist-info/WHEEL
unet-0.8.0.dist-info/licenses/LICENSE
unet-0.8.0.dist-info/RECORD
