Metadata-Version: 2.3
Name: unet
Version: 0.8.0
Summary: PyTorch implementation of 1D, 2D and 3D U-Net.
Project-URL: Homepage, https://github.com/fepegar/unet
Project-URL: Source, https://github.com/fepegar/unet
Project-URL: Issue tracker, https://github.com/fepegar/unet/issues
Author-email: Fernando Perez-Garcia <fepegar@gmail.com>
Classifier: Intended Audience :: Science/Research
Classifier: License :: OSI Approved :: MIT License
Classifier: Natural Language :: English
Classifier: Operating System :: OS Independent
Classifier: Programming Language :: Python :: 3.9
Classifier: Programming Language :: Python :: 3.10
Classifier: Programming Language :: Python :: 3.11
Classifier: Programming Language :: Python :: 3.12
Requires-Python: <3.13,>=3.9
Requires-Dist: torch
